ml_model_manager/__init__.py
ml_model_manager/main.py
ml_model_manager-0.1.2.dist-info/licenses/LICENSE
ml_model_manager-0.1.2.dist-info/METADATA
ml_model_manager-0.1.2.dist-info/WHEEL
ml_model_manager-0.1.2.dist-info/top_level.txt
ml_model_manager-0.1.2.dist-info/RECORD
