Metadata-Version: 2.4
Name: ml_model_manager
Version: 0.1.2
Summary: A simple library to train, manage, and use multiple ML models easily.
Home-page: https://github.com/rucha-ambaliya/ml_model_manager
Author: Rucha Ambaliya
Author-email: ruchaambaliya@example.com
Classifier: Programming Language :: Python :: 3
Classifier: License :: OSI Approved :: MIT License
Classifier: Operating System :: OS Independent
Requires-Python: >=3.7
License-File: LICENSE
Requires-Dist: pandas
Requires-Dist: scikit-learn
Requires-Dist: xgboost
Dynamic: author
Dynamic: author-email
Dynamic: classifier
Dynamic: description
Dynamic: description-content-type
Dynamic: home-page
Dynamic: license-file
Dynamic: requires-dist
Dynamic: requires-python
Dynamic: summary
